{
  "base_price": 2995,
  "beamstation_catalog_url": "https://beamstation.com/datasets",
  "beamstation_origin": "https://beamstation.com",
  "category_group_name": "Food and Drink",
  "config_category": "expansion",
  "config_description": "--Distressed Venues with Verified Decline--\n\nEstablished, well-reviewed restaurants, bars, and cafes now experiencing a sharp and confirmed drop in Transaction Velocity & Customer Sentiment.\n\nThese are previously high-performing venues where the 360-day sentiment was strong, but 90-day sentiment has crashed by 30%+.\n\nThat's a leading indicator of operational trouble, ownership fatigue, or market-ready distress.\n\nEvery listing is an independent hospitality and food & beverage location (no nation-wide chains), confirmed active with 100+ total reviews and an \"Active Heartbeat\" signal within the last 90 days.",
  "config_name": "Independent Restaurants Experiencing a 30%+ Crash in Foot Traffic & Sentiment This Quarter in Minnesota",
  "export_job_id": "d990c475-32e5-472d-98c4-ee7c1f94c637",
  "github_org": "Beamstation-Datasets",
  "id_short": 393250,
  "location_name": "Minnesota",
  "location_type": "state",
  "repo_name": "independent-restaurants-experiencing-a-30-crash-in-foot-traffic-sentiment-this-qua-sample-393250",
  "sample_b2_path": "b2-export:BeamStation-ExportFiles/393250/beamstation_393250_food_and_drink-us-mn_SAMPLE_DIST.csv",
  "sample_pct": 9.9,
  "sample_records": 40,
  "sample_sha256": "bd50598f5c54ad131d5126c4a96fbfecc7e93584b329f956b85820639622d1cf",
  "sample_size_bytes": 171116,
  "total_records": 404,
  "updated_at": "2026-04-09T19:00:19.109290+00:00"
}